[{"name": "零基础入门数据挖掘 - 二手车交易价格预测(赛季 1)", "url": "https://tianchi.aliyun.com/competition/entrance/231784/introduction", "description": "本次赛事是Datawhale与天池共同发起的零基础入门系列赛事第一场 —— 零基础入门数据挖掘-二手车交易价格预测，赛题以二手车市场为背景，要求选手预测二手汽车的交易价格，这是一个典型的回归问题。", "deadline": "2020-03-31T19:30:00+08:00", "reward": "￥0", "start_time": "2020-03-12T18:55:00+08:00"}, {"name": "微博立场检测", "url": "https://god.yanxishe.com/44", "description": "微博立场检测是一个新兴的研究课题，判断微博作者对某个话题是持何种立场，立场有三种：FAVOR支持，AGAINST反对，NONE两者都不是", "deadline": "2020-04-12T23:59:59+08:00", "reward": "3000.00", "start_time": "2020-03-13T16:46:17+08:00"}]